{
  "header": "¶ <em>A Psalm</em> of David, when he changed his behaviour before Abimelech; who drove him away, and he departed.",
  "footer": "",
  "verses": [
    {
      "book_id": "PSA",
      "book_name": "Psalms",
      "chapter": 34,
      "verse": 1,
      "text": "I will bless the LORD at all times: his praise <em>shall</em> continually <em>be</em> in my mouth.",
      "info": ""
    },
    {
      "book_id": "PSA",
      "book_name": "Psalms",
      "chapter": 34,
      "verse": 2,
      "text": "My soul shall make her boast in the LORD: the humble shall hear <em>thereof,</em> and be glad.",
      "info": ""
    },
    {
      "book_id": "PSA",
      "book_name": "Psalms",
      "chapter": 34,
      "verse": 3,
      "text": "O magnify the LORD with me, and let us exalt his name together.",
      "info": ""
    },
    {
      "book_id": "PSA",
      "book_name": "Psalms",
      "chapter": 34,
      "verse": 4,
      "text": "I sought the LORD, and he heard me, and delivered me from all my fears.",
      "info": ""
    },
    {
      "book_id": "PSA",
      "book_name": "Psalms",
      "chapter": 34,
      "verse": 5,
      "text": "They looked unto him, and were lightened: and their faces were not ashamed.",
      "info": ""
    },
    {
      "book_id": "PSA",
      "book_name": "Psalms",
      "chapter": 34,
      "verse": 6,
      "text": "This poor man cried, and the LORD heard <em>him,</em> and saved him out of all his troubles.",
      "info": ""
    },
    {
      "book_id": "PSA",
      "book_name": "Psalms",
      "chapter": 34,
      "verse": 7,
      "text": "The angel of the LORD encampeth round about them that fear him, and delivereth them.",
      "info": ""
    },
    {
      "book_id": "PSA",
      "book_name": "Psalms",
      "chapter": 34,
      "verse": 8,
      "text": "O taste and see that the LORD <em>is</em> good: blessed <em>is</em> the man <em>that</em> trusteth in him.",
      "info": ""
    },
    {
      "book_id": "PSA",
      "book_name": "Psalms",
      "chapter": 34,
      "verse": 9,
      "text": "O fear the LORD, ye his saints: for <em>there is</em> no want to them that fear him.",
      "info": ""
    },
    {
      "book_id": "PSA",
      "book_name": "Psalms",
      "chapter": 34,
      "verse": 10,
      "text": "The young lions do lack, and suffer hunger: but they that seek the LORD shall not want any good <em>thing.</em>",
      "info": ""
    },
    {
      "book_id": "PSA",
      "book_name": "Psalms",
      "chapter": 34,
      "verse": 11,
      "text": "Come, ye children, hearken unto me: I will teach you the fear of the LORD.",
      "info": ""
    },
    {
      "book_id": "PSA",
      "book_name": "Psalms",
      "chapter": 34,
      "verse": 12,
      "text": "What man <em>is he that</em> desireth life, <em>and</em> loveth <em>many</em> days, that he may see good?",
      "info": ""
    },
    {
      "book_id": "PSA",
      "book_name": "Psalms",
      "chapter": 34,
      "verse": 13,
      "text": "Keep thy tongue from evil, and thy lips from speaking guile.",
      "info": ""
    },
    {
      "book_id": "PSA",
      "book_name": "Psalms",
      "chapter": 34,
      "verse": 14,
      "text": "Depart from evil, and do good; seek peace, and pursue it.",
      "info": ""
    },
    {
      "book_id": "PSA",
      "book_name": "Psalms",
      "chapter": 34,
      "verse": 15,
      "text": "The eyes of the LORD <em>are</em> upon the righteous, and his ears <em>are open</em> unto their cry.",
      "info": ""
    },
    {
      "book_id": "PSA",
      "book_name": "Psalms",
      "chapter": 34,
      "verse": 16,
      "text": "The face of the LORD <em>is</em> against them that do evil, to cut off the remembrance of them from the earth.",
      "info": ""
    },
    {
      "book_id": "PSA",
      "book_name": "Psalms",
      "chapter": 34,
      "verse": 17,
      "text": "<em>The righteous</em> cry, and the LORD heareth, and delivereth them out of all their troubles.",
      "info": ""
    },
    {
      "book_id": "PSA",
      "book_name": "Psalms",
      "chapter": 34,
      "verse": 18,
      "text": "The LORD <em>is</em> nigh unto them that are of a broken heart; and saveth such as be of a contrite spirit.",
      "info": ""
    },
    {
      "book_id": "PSA",
      "book_name": "Psalms",
      "chapter": 34,
      "verse": 19,
      "text": "Many <em>are</em> the afflictions of the righteous: but the LORD delivereth him out of them all.",
      "info": ""
    },
    {
      "book_id": "PSA",
      "book_name": "Psalms",
      "chapter": 34,
      "verse": 20,
      "text": "He keepeth all his bones: not one of them is broken.",
      "info": ""
    },
    {
      "book_id": "PSA",
      "book_name": "Psalms",
      "chapter": 34,
      "verse": 21,
      "text": "Evil shall slay the wicked: and they that hate the righteous shall be desolate.",
      "info": ""
    },
    {
      "book_id": "PSA",
      "book_name": "Psalms",
      "chapter": 34,
      "verse": 22,
      "text": "The LORD redeemeth the soul of his servants: and none of them that trust in him shall be desolate.",
      "info": ""
    }
  ]
}