{
  "header": "¶ To the chief Musician, A Psalm of David, when Nathan the prophet came unto him, after he had gone in to Bathsheba.",
  "footer": "",
  "verses": [
    {
      "book_id": "PSA",
      "book_name": "Psalms",
      "chapter": 51,
      "verse": 1,
      "text": "Have mercy upon me, O God, according to thy lovingkindness: according unto the multitude of thy tender mercies blot out my transgressions.",
      "info": ""
    },
    {
      "book_id": "PSA",
      "book_name": "Psalms",
      "chapter": 51,
      "verse": 2,
      "text": "Wash me throughly from mine iniquity, and cleanse me from my sin.",
      "info": ""
    },
    {
      "book_id": "PSA",
      "book_name": "Psalms",
      "chapter": 51,
      "verse": 3,
      "text": "For I acknowledge my transgressions: and my sin <em>is</em> ever before me.",
      "info": ""
    },
    {
      "book_id": "PSA",
      "book_name": "Psalms",
      "chapter": 51,
      "verse": 4,
      "text": "Against thee, thee only, have I sinned, and done <em>this</em> evil in thy sight: that thou mightest be justified when thou speakest, <em>and</em> be clear when thou judgest.",
      "info": ""
    },
    {
      "book_id": "PSA",
      "book_name": "Psalms",
      "chapter": 51,
      "verse": 5,
      "text": "Behold, I was shapen in iniquity; and in sin did my mother conceive me.",
      "info": ""
    },
    {
      "book_id": "PSA",
      "book_name": "Psalms",
      "chapter": 51,
      "verse": 6,
      "text": "Behold, thou desirest truth in the inward parts: and in the hidden <em>part</em> thou shalt make me to know wisdom.",
      "info": ""
    },
    {
      "book_id": "PSA",
      "book_name": "Psalms",
      "chapter": 51,
      "verse": 7,
      "text": "Purge me with hyssop, and I shall be clean: wash me, and I shall be whiter than snow.",
      "info": ""
    },
    {
      "book_id": "PSA",
      "book_name": "Psalms",
      "chapter": 51,
      "verse": 8,
      "text": "Make me to hear joy and gladness; <em>that</em> the bones <em>which</em> thou hast broken may rejoice.",
      "info": ""
    },
    {
      "book_id": "PSA",
      "book_name": "Psalms",
      "chapter": 51,
      "verse": 9,
      "text": "Hide thy face from my sins, and blot out all mine iniquities.",
      "info": ""
    },
    {
      "book_id": "PSA",
      "book_name": "Psalms",
      "chapter": 51,
      "verse": 10,
      "text": "Create in me a clean heart, O God; and renew a right spirit within me.",
      "info": ""
    },
    {
      "book_id": "PSA",
      "book_name": "Psalms",
      "chapter": 51,
      "verse": 11,
      "text": "Cast me not away from thy presence; and take not thy holy spirit from me.",
      "info": ""
    },
    {
      "book_id": "PSA",
      "book_name": "Psalms",
      "chapter": 51,
      "verse": 12,
      "text": "Restore unto me the joy of thy salvation; and uphold me <em>with thy</em> free spirit.",
      "info": ""
    },
    {
      "book_id": "PSA",
      "book_name": "Psalms",
      "chapter": 51,
      "verse": 13,
      "text": "<em>Then</em> will I teach transgressors thy ways; and sinners shall be converted unto thee.",
      "info": ""
    },
    {
      "book_id": "PSA",
      "book_name": "Psalms",
      "chapter": 51,
      "verse": 14,
      "text": "Deliver me from bloodguiltiness, O God, thou God of my salvation: <em>and</em> my tongue shall sing aloud of thy righteousness.",
      "info": ""
    },
    {
      "book_id": "PSA",
      "book_name": "Psalms",
      "chapter": 51,
      "verse": 15,
      "text": "O Lord, open thou my lips; and my mouth shall shew forth thy praise.",
      "info": ""
    },
    {
      "book_id": "PSA",
      "book_name": "Psalms",
      "chapter": 51,
      "verse": 16,
      "text": "For thou desirest not sacrifice; else would I give <em>it:</em> thou delightest not in burnt offering.",
      "info": ""
    },
    {
      "book_id": "PSA",
      "book_name": "Psalms",
      "chapter": 51,
      "verse": 17,
      "text": "The sacrifices of God <em>are</em> a broken spirit: a broken and a contrite heart, O God, thou wilt not despise.",
      "info": ""
    },
    {
      "book_id": "PSA",
      "book_name": "Psalms",
      "chapter": 51,
      "verse": 18,
      "text": "Do good in thy good pleasure unto Zion: build thou the walls of Jerusalem.",
      "info": ""
    },
    {
      "book_id": "PSA",
      "book_name": "Psalms",
      "chapter": 51,
      "verse": 19,
      "text": "Then shalt thou be pleased with the sacrifices of righteousness, with burnt offering and whole burnt offering: then shall they offer bullocks upon thine altar.",
      "info": ""
    }
  ]
}