{
  "header": "¶ To the chief Musician upon Shushaneduth, Michtam of David, to teach; when he strove with Aramnaharaim and with Aramzobah, when Joab returned, and smote of Edom in the valley of salt twelve thousand.",
  "footer": "",
  "verses": [
    {
      "book_id": "PSA",
      "book_name": "Psalms",
      "chapter": 60,
      "verse": 1,
      "text": "O God, thou hast cast us off, thou hast scattered us, thou hast been displeased; O turn thyself to us again.",
      "info": ""
    },
    {
      "book_id": "PSA",
      "book_name": "Psalms",
      "chapter": 60,
      "verse": 2,
      "text": "Thou hast made the earth to tremble; thou hast broken it: heal the breaches thereof; for it shaketh.",
      "info": ""
    },
    {
      "book_id": "PSA",
      "book_name": "Psalms",
      "chapter": 60,
      "verse": 3,
      "text": "Thou hast shewed thy people hard things: thou hast made us to drink the wine of astonishment.",
      "info": ""
    },
    {
      "book_id": "PSA",
      "book_name": "Psalms",
      "chapter": 60,
      "verse": 4,
      "text": "Thou hast given a banner to them that fear thee, that it may be displayed because of the truth. Selah.",
      "info": ""
    },
    {
      "book_id": "PSA",
      "book_name": "Psalms",
      "chapter": 60,
      "verse": 5,
      "text": "That thy beloved may be delivered; save <em>with</em> thy right hand, and hear me.",
      "info": ""
    },
    {
      "book_id": "PSA",
      "book_name": "Psalms",
      "chapter": 60,
      "verse": 6,
      "text": "God hath spoken in his holiness; I will rejoice, I will divide Shechem, and mete out the valley of Succoth.",
      "info": ""
    },
    {
      "book_id": "PSA",
      "book_name": "Psalms",
      "chapter": 60,
      "verse": 7,
      "text": "Gilead <em>is</em> mine, and Manasseh <em>is</em> mine; Ephraim also <em>is</em> the strength of mine head; Judah <em>is</em> my lawgiver;",
      "info": ""
    },
    {
      "book_id": "PSA",
      "book_name": "Psalms",
      "chapter": 60,
      "verse": 8,
      "text": "Moab <em>is</em> my washpot; over Edom will I cast out my shoe: Philistia, triumph thou because of me.",
      "info": ""
    },
    {
      "book_id": "PSA",
      "book_name": "Psalms",
      "chapter": 60,
      "verse": 9,
      "text": "Who will bring me <em>into</em> the strong city? who will lead me into Edom?",
      "info": ""
    },
    {
      "book_id": "PSA",
      "book_name": "Psalms",
      "chapter": 60,
      "verse": 10,
      "text": "<em>Wilt</em> not thou, O God, <em>which</em> hadst cast us off? and <em>thou,</em> O God, <em>which</em> didst not go out with our armies?",
      "info": ""
    },
    {
      "book_id": "PSA",
      "book_name": "Psalms",
      "chapter": 60,
      "verse": 11,
      "text": "Give us help from trouble: for vain <em>is</em> the help of man.",
      "info": ""
    },
    {
      "book_id": "PSA",
      "book_name": "Psalms",
      "chapter": 60,
      "verse": 12,
      "text": "Through God we shall do valiantly: for he <em>it is that</em> shall tread down our enemies.",
      "info": ""
    }
  ]
}