{
  "header": "¶ To the chief Musician, Altaschith, A Psalm <em>or</em> Song of Asaph.",
  "footer": "",
  "verses": [
    {
      "book_id": "PSA",
      "book_name": "Psalms",
      "chapter": 75,
      "verse": 1,
      "text": "Unto thee, O God, do we give thanks, <em>unto thee</em> do we give thanks: for <em>that</em> thy name is near thy wondrous works declare.",
      "info": ""
    },
    {
      "book_id": "PSA",
      "book_name": "Psalms",
      "chapter": 75,
      "verse": 2,
      "text": "When I shall receive the congregation I will judge uprightly.",
      "info": ""
    },
    {
      "book_id": "PSA",
      "book_name": "Psalms",
      "chapter": 75,
      "verse": 3,
      "text": "The earth and all the inhabitants thereof are dissolved: I bear up the pillars of it. Selah.",
      "info": ""
    },
    {
      "book_id": "PSA",
      "book_name": "Psalms",
      "chapter": 75,
      "verse": 4,
      "text": "I said unto the fools, Deal not foolishly: and to the wicked, Lift not up the horn:",
      "info": ""
    },
    {
      "book_id": "PSA",
      "book_name": "Psalms",
      "chapter": 75,
      "verse": 5,
      "text": "Lift not up your horn on high: speak <em>not with</em> a stiff neck.",
      "info": ""
    },
    {
      "book_id": "PSA",
      "book_name": "Psalms",
      "chapter": 75,
      "verse": 6,
      "text": "For promotion <em>cometh</em> neither from the east, nor from the west, nor from the south.",
      "info": ""
    },
    {
      "book_id": "PSA",
      "book_name": "Psalms",
      "chapter": 75,
      "verse": 7,
      "text": "But God <em>is</em> the judge: he putteth down one, and setteth up another.",
      "info": ""
    },
    {
      "book_id": "PSA",
      "book_name": "Psalms",
      "chapter": 75,
      "verse": 8,
      "text": "For in the hand of the LORD <em>there is</em> a cup, and the wine is red; it is full of mixture; and he poureth out of the same: but the dregs thereof, all the wicked of the earth shall wring <em>them</em> out, <em>and</em> drink <em>them.</em>",
      "info": ""
    },
    {
      "book_id": "PSA",
      "book_name": "Psalms",
      "chapter": 75,
      "verse": 9,
      "text": "But I will declare for ever; I will sing praises to the God of Jacob.",
      "info": ""
    },
    {
      "book_id": "PSA",
      "book_name": "Psalms",
      "chapter": 75,
      "verse": 10,
      "text": "All the horns of the wicked also will I cut off; <em>but</em> the horns of the righteous shall be exalted.",
      "info": ""
    }
  ]
}